MANIFEST.in
README.md
setup.cfg
setup.py
dense_fusion/__init__.py
dense_fusion.egg-info/PKG-INFO
dense_fusion.egg-info/SOURCES.txt
dense_fusion.egg-info/dependency_links.txt
dense_fusion.egg-info/not-zip-safe
dense_fusion.egg-info/requires.txt
dense_fusion.egg-info/top_level.txt
dense_fusion/data/__init__.py
dense_fusion/data/pretrained_model.py
dense_fusion/datasets/__init__.py
dense_fusion/datasets/ycb/__init__.py
dense_fusion/datasets/ycb/ycb_utils.py
dense_fusion/datasets/ycb/ycb_video_dataset.py
dense_fusion/datasets/ycb/config/README.md
dense_fusion/datasets/ycb/config/classes.txt
dense_fusion/datasets/ycb/config/test_data_list.txt
dense_fusion/datasets/ycb/config/train_data_list.txt
dense_fusion/models/__init__.py
dense_fusion/models/network.py
dense_fusion/models/pspnet.py
dense_fusion/models/resnet.py
dense_fusion/nn/__init__.py
dense_fusion/nn/loss.py
dense_fusion/visualizations/__init__.py
dense_fusion/visualizations/vis_bboxes.py
dense_fusion/visualizations/vis_pcd.py