Metadata-Version: 2.1
Name: dense-fusion
Version: 0.0.3
Summary: DenseFusion (6DoF Pose Estimaton)
Home-page: https://github.com/iory/dense-fusion
Author: iory
Author-email: ab.ioryz@gmail.com
License: MIT
Platform: UNKNOWN
Classifier: Development Status :: 5 - Production/Stable
Classifier: Intended Audience :: Developers
Classifier: Natural Language :: English
Classifier: License :: OSI Approved :: MIT License
Classifier: Programming Language :: Python
Classifier: Programming Language :: Python :: 2.7
Classifier: Programming Language :: Python :: 3.5
Classifier: Programming Language :: Python :: 3.6
Classifier: Programming Language :: Python :: 3.7
Classifier: Programming Language :: Python :: Implementation :: CPython
